{
  "mongo_id": "689ccad49f52327be8e0f96d",
  "doc_id": "e44733ac-1b2b-4494-bf20-4150da6586e3",
  "doc_hash": "2ed292393f2791049b1a01a42f731e97ff1b16812c0137648f4a99cce93ea5f0",
  "file_name": "tmpj5qg5wv2.pdf",
  "num_pages": 8,
  "preview": [
    "data\\images\\tmpj5qg5wv2\\thumb_tmpj5qg5wv2_page0001.png",
    "data\\images\\tmpj5qg5wv2\\thumb_tmpj5qg5wv2_page0002.png",
    "data\\images\\tmpj5qg5wv2\\thumb_tmpj5qg5wv2_page0003.png",
    "data\\images\\tmpj5qg5wv2\\thumb_tmpj5qg5wv2_page0004.png",
    "data\\images\\tmpj5qg5wv2\\thumb_tmpj5qg5wv2_page0005.png",
    "data\\images\\tmpj5qg5wv2\\thumb_tmpj5qg5wv2_page0006.png",
    "data\\images\\tmpj5qg5wv2\\thumb_tmpj5qg5wv2_page0007.png",
    "data\\images\\tmpj5qg5wv2\\thumb_tmpj5qg5wv2_page0008.png"
  ],
  "text": "2025년 개발자 취업 시장을 위한 가이드 < 개발자 이력서 /> 성공적인 경력을 위한 작성 가이드 기술 스택 프로젝트 경력 교육 기술적 역량을 효과적으로 전달하는 이력서 작성법\n\n개발자 이력서 작성의 기본 이력서의 핵심 구성 요소와 효과적인 작성 방법 연락처 및 기본 정보 이름 :  전체 이름 명확히 기재 이메일 :  닉네임 없는 전문적 주소 전화번호 :  연락 가능한 번호 거주지 :  시 / 구 단위로 기재 포트폴리오 링크 : GitHub,  개인 사이트 필수 기술 스택 프로그래밍 언어 : Python, Java, JavaScript 등 프레임워크 : React, Node.js, Django  등 데이터베이스 : PostgreSQL, MongoDB, MySQL  등 DevOps &  클라우드 : Docker, Kubernetes, AWS  등 *  기술은 사용한 경험이 있는 것부터 우선순위로 경력 사항 회사명 ,  직책 ,  근무 기간 ,  위치 주요 성과  3~5 개의  bullet point 행동 동사로 시작 : \" 개발 \", \" 개선 \", \" 구축 \" 성과 수치화 : \"API  응답 시간  35%  단축 \" 사용한 기술 명시 프로젝트 경험 프로젝트명 및 기술 스택 프로젝트 목적 및 주요 기능 구체적인 역할과 기여 성과 및 결과 ( 사용자 수 ,  성능 개선 ) 관련 링크 (GitHub,  라이브 서비스 ) 교육 및 자격증 학력 :  최종 학력 순으로 학교명 ,  전공 ,  졸업 연 도 학점 : 4.5 만점에  4.0 이상인 경우 기재 자격증 : AWS Certified, CKAD  등  IT  자격증 수강 과목 :  관련성 높은 과목만 선택 작성 팁 이름 아래에 전문 분야 요약 추가 기술 스택은 별도 섹션으로 구성 경력은 가장 최근부터 역순으로 작성 프로젝트는 결과물을 확인할 수 있는 링크 포 함 간결하고 ,  명확하며 ,  직무와 관련성 높은 내용\n\n연락처 및 기술 스택 구성 전문적인 정보 표현으로 채용 담당자의 관심을 끄는 방법 연락처 정보 작성 이름 전체 이름을 명확하게 기재합니다 . 예 : \" 홍길동 \" 이메일 주소 닉네임이나 비전문적인 단어가 포함되지 않은 개인 이메일 주소를 사용 합니다 . 예 : \"gildong.hong@example.com\" 전화번호 연락 가능한 개인 전화번호를 기재합니다 . 예 : \"010-1234-5678\" 거주지 전체 주소 대신 시와 구 단위까지만 기재하는 것이 일반적입니다 . 예 : \" 서울특별시 강남구 \" 기술 스택 구성 프로그래밍 언어  (Languages) Python, Java, JavaScript, Go, C++  등 숙련도 높은 언어 순으로 기재합니 다 . 프레임워크 및 라이브러리  (Frameworks & Libraries) React, Node.js, Django, Spring  등 사용 경험이 있는 기술을 명시합니다 . 데이터베이스  (Databases) PostgreSQL, MongoDB, MySQL, Redis  등 관련 기술을 나열합니다 . DevOps  및 클라우드  (DevOps & Cloud) Docker, Kubernetes, AWS, Git, CI/CD  등 관련 도구와 플랫폼을 포함합니 다 . 포트폴리오 링크의 중요성 GitHub,  개인 웹사이트 ,  기술 블로그 등 자신의 코딩 실력과 프로젝트를 보여줄 수 있는 링크를 반드시 포함 합니다 .  특히  GitHub  프로필은 개발자의 필수 요소로 여겨 집니다 .  GitHub  개인 웹사이트  기술 블로그\n\n경력 및 프로젝트 작성법 구체적인 성과 중심으로 작성하는 방법과 수치화된 결과 제시 전략 경력 사항 작성법 구조와 포맷 회사명 ,  직책 ,  근무 기간 ,  위치 주요 성과 :  3~5 개의  bullet point 성과 작성 팁 행동 동사로 시작 : \" 개발 \", \" 개선 \", \" 구축 \" 구체적인 수치로 결과 표현 사용한 기술 명시 예시 나쁜 예 : 프론트엔드 개발 업무를 담당함 . 좋은 예 :  React  컴포넌트 리팩토링을 통해 웹 애플리케이션 로딩 속도를 50% 개선하고 사용자 경험을 향상시킴 . 프로젝트 경험 작성법 필요한 정보 프로젝트명 및 기술 스택 프로젝트 설명 ( 목적 ,  주요 기능 ) 구체적인 역할과 기여 성과 및 결과 ( 사용자 수 ,  성능 개선 ) 관련 링크 (GitHub,  라이브 서비스 ) 예시 나쁜 예 : 팀 프로젝트에서 로그인 기능 개발 좋은 예 :  OAuth 2.0 을 활용한 사용자 인증 시스템을 구현하여 로그인 실패율 30% 감소 수치화된 결과 제시 전략 구체적  +  동사  +  숫자  +  결과 \" 페이지 로딩 속도 40% 단축 \"  키 포인트 : 채용 담당자는 단순히 수행한 업무보다 구체적인 성과와 기여 에 더 관심을 가짐 .  가능한 모든 성과를 숫자로 표현하여 영향력을 강조 하라 .\n\n이력서 작성 시 주의사항 주의할 점들과 팁 불필요한 정보 배제 채용 담당자는 수많은 이력서를 검토해야 하므로 ,  핵심 정보에 집중할 수 있도록 간결하고 전문성 있는 내용으로 구성해야 합니다 . 개인 신상 정보 :  사진 ,  나이 ,  결혼 여부 ,  국적 등 관련 없는 취미 및 관심사 불필요한 경력 :  직무와 관련 없는 과거 경력 추천인 정보 : \" 추천인 정보는 요청 시 제공 가능 \"  같은 문구 구체적인 성과 제시 추상적인 표현보다 수치화된 데이터를 활용하여 자신의 기여도를 명확 하게 보여주는 것이 중요합니다 . 성과 작성 공식 : \" 강력한 동사  +  수행한 업무  +  수치화된 결과 \" 나쁜 예 : 웹사이트 성능 개선 작업 참여 좋은 예 : 데이터베이스 쿼리 최적화 및 캐싱 전략 도입으로 페이지 로딩 속도  40%  단축 키워드 최적화  (ATS  대응 ) 약  98% 의 기업은 지원자 추적 시스템 (ATS) 을 사용하여 이력서를  1 차적 으로 선별합니다 .  채용 공고의 키워드와 일치하는 이력서를 찾아냅니다 . 채용 공고를 면밀히 분석하여 핵심 기술 ,  자격 요건을 파악 공고에 명시된 키워드를 자연스럽게 포함 약어와 전체 용어 병기  ( 예 : \"Amazon Web Services (AWS)\") 지원 직무에 맞춰 키워드와 내용 미세 조정 가독성 향상 이력서는  ATS 뿐만 아니라 최종적으로 사람이 읽는 문서입니다 .  채용 담 당자가 짧은 시간 안에 핵심 정보를 파악할 수 있도록 가독성을 높이는 것이 매우 중요합니다 . 단순한 형식 유지 :  복잡한 레이아웃보다는 간결한 단일 열 (single- column)  레이아웃 표준 글꼴 사용 : Arial, Calibri, Times New Roman  등  10-12pt  크기 명확한 섹션 구분 : \"Work Experience\", \"Skills\"  등 표준 제목 사용 일관성 있는 서식 :  날짜 형식 ,  글머리 기호 ,  볼드체 사용 등 일관성 유 지 오탈자 및 문법 오류 확인 :  제출 전 여러 번 검토  이력서는 전략적인 마케팅 도구이므로 ,  자신의 강점을 전략적으로 어필하는 것이 가장 중요합니다 .\n\n경력별 이력서 작성 전략 각 경력 단계에서 강조해야 할 핵심 요소 신입 개발자 잠재력을 증명하고 기본기를 보여주는 것이 핵심 1 학업 성과 및 교육 강조  ( 컴퓨터 공학 ,  부트 캠프 ) 2 인턴십 및 실제 경험  ( 비록 짧더라도 구체적 ) 3 프로젝트 경험 부각  ( 개인 ,  팀 ,  오픈소스 기 여 ) 4 기술 스택과 관련 수강 과목 채용 담당자가 확인하려는 것 :  성장 가능성 ,  문제 해결 능력 주니어 개발자 실무 경험을 통해 기술 적용 능력을 증명 1 실무 경험 중심 구성  ( 경력 사항이 가장 중 요 ) 2 성과 수치화  ( 예 : \"API  응답 시간  20%  단축 \") 3 기술 스택과 문제 해결 능력 연결 4 최근  1-3 년의 경력에 초점을 맞추어  3~5 개 의 핵심 성과 채용 담당자가 확인하려는 것 :  기술적 역량 ,  실무 경험 시니어 개발자 리더십 ,  멘토링 ,  프로젝트 관리 능력을 강조 1 리더십과 관리 경험 강조  ( 팀 이끄기 ,  멘토 링 ) 2 비즈니스 임팩트 중심의 성과  ( 예 : \" 시스템 다운타임  70%  감소 \") 3 기술적 깊이와 아키텍처 설계 능력 4 간결하고 핵심적인 구성  ( 첫 페이지에 가장 중요한 내용 ) 채용 담당자가 확인하려는 것 :  팀 리더십 ,  비즈니 스 기여\n\n온라인 프로필 및 포트폴리오 연계 이력서와 함께하는 강력한 증거 자료로의 역할 GitHub  프로필 개발자의 실질적인 코딩 능력을 보여주는 가장 중요한 포트폴리오 프로필  README  활용 자신을 소개하고 주요 기술 스택 요약 주요 프로젝트 고정 (Pin) 지원하는 직무와 관련성 높은 프로젝트를 프로필 상 단에 고정 프로젝트별  README  작성 프로젝트 목적 ,  기술 ,  실행 방법 ,  자신의 기여도 상세 히 설명 코드 품질 및 기여도 깔끔하고 주석이 잘 달린 코드 ,  오픈 소스에 기여하면 협업 능력 증명 LinkedIn  프로필 전문적인 네트워크를 구축하고 경력을 관리하는 필수 적 플랫폼 전문성 있는 프로필 이력서와 일관성 있는 경력 ,  학력 ,  기술 스택을 기재 네트워크 및 추천서 업계 전문가들과의 네트워크 ,  이전 동료나 상사의 추 천서 기술 및 보증 (Skills & Endorsements) 핵심 기술 목록화하고 동료들로부터 보증 받으면 기 술적 신뢰성 강화 꾸준한 활동 기술 관련 아티클 공유하거나 토론에 참여하는 등 꾸 준한 활동 개인 블로그 / 포트폴리오 자신만의 브랜드를 구축하고 전문성을 깊이 있게 보여 줄 수 있는 공간 기술 블로그 운영 특정 기술에 대한 문제 해결 과정 ,  새로운 기술 학습 기 ,  프로젝트 회고 프로젝트 쇼케이스 대표 프로젝트들을 시각적으로 매력적이게 소개하는 포트폴리오 페이지 디자인 및 사용자 경험 포트폴리오 사이트 자체의 디자인과  UX 도 평가의 대 상이 될 수 있습니다 이력서 및 연락처 정보 포함 방문자가 쉽게 이력서를 다운로드하고 연락할 수 있 도록 관련 정보 명확히 기재 이력서와의 효과적인 연계 이력서에  GitHub  프로필 링크 필수 포함 LinkedIn  프로필에서 이력서 첨부하거나 링크 제 공 개인 포트폴리오에 지원하는 직무와 관련된 최적 화된 이력서 버전 링크\n\n이력서 검토 및 개선 방법 피드백을 통한 개선과 지속적인 업데이트의 중요성 피드백 수렴 자신이 작성한 문서의 오류를 스스로 찾아내기란 쉽지 않습니다 .  다양한 관 점의 피드백은 이력서의 완성도를 높이는 데 결정적인 역할을 합니다 . 동료 및 스터디 그룹 기술적인 내용의 정확성을 검증하고 , 프로젝트 경험이 명확하게 설명되었 는지 확인 멘토 및 선배 개발자 경력 기술 방식 ,  성과 부각 방법 등 전략적인 관점에서 조언 온라인 커뮤니티 Tech Interview Handbook  등 개발자 커뮤니티에서 이력서 리뷰를 서로 공 유 효과적인 피드백 요청 구체적인 조언을 구하는 것이 아니 라 ,  지원하는 직무와 회사 정보를 제 공 지속적인 업데이트 이력서는 한 번 만들고 끝나는 문서가 아니라 ,  자신의 성장을 담아내는 살아 있는 기록입니다 .  새로운 기술을 습득하거나 프로젝트를 완료할 때마다 이 력서를 꾸준히 업데이트하는 습관을 들이는 것이 중요합니다 . 잘 만들어진 이력서는 개발자로서의 전문성과 가치를 보여주는 가장 기본적인 도구입니다 .  객관적인 피드백을 통해 완성도를 높이고 ,  자신의 성 장 과정을 꾸준히 반영하여 항상 최상의 상태를 유지하는 노력이 성공적인 구직 활동의 핵심이라 할 수 있습니다 .  새로운 기술 및 프로젝트 반영 새로운 프로그래밍 언어 ,  프레임워크를 학습하거나 의미 있는 프로젝트를 마쳤을 때 즉시 이력서에 추가 성과 기록 현재 진행 중인 업무에서 달성한 성과 ( 성능 개선 수치 ,  비용 절감 효과 등 ) 를 정기 적으로 기록하고 반영 맞춤형 수정 이력서를 최신 상태로 유지하면 ,  새로운 채용 공고가 나왔을 때 해당 직무에 맞춰 빠르고 효과적으로 내용을 수정 8/8",
  "fields": {
    "emails": [
      "gildong.hong@example.com"
    ],
    "phones": [
      "010-1234-5678"
    ],
    "dates": [],
    "numbers": [],
    "urls": [],
    "names": [
      "학업"
    ],
    "positions": [
      "자의 관심을 끄는 방법 연락처 정보 작성 이름 전체 이름을 명확하게 기재합니다",
      "자는 단순히 수행한 업무보다 구체적인 성과와 기여 에 더 관심을 가짐",
      "자는 수많은 이력서를 검토해야 하므로",
      "자가 확인하려는 것",
      "개발자",
      "pl",
      "함"
    ],
    "companies": [
      "정보를 제 공 지속적인 업데이트 이력서는 한 번 만들고 끝나는 문서가 아니라",
      "기간",
      "명"
    ],
    "education": [
      "최종 학력 순으로 학교명"
    ],
    "skills": [
      "블로그 운영 특정 기술에 대한 문제 해결 과정 ,  새로운 기술 학습 기 ,  프로젝트 회고 프로젝트 쇼케이스 대표 프로젝트들을 시각적으로 매력적이게 소개하는 포트폴리오 페이지 디자인 및 사용자 경험 포트폴리오 사이트 자체의 디자인과  UX 도 평가의 대 상이 될 수 있습니다 이력서 및 연락처 정보 포함 방문자가 쉽게 이력서를 다운로드하고 연락할 수 있 도록 관련 정보 명확히 기재 이력서와의 효과적인 연계 이력서에  GitHub  프로필 링크 필수 포함 LinkedIn  프로필에서 이력서 첨부하거나 링크 제 공 개인 포트폴리오에 지원하는 직무와 관련된 최적 화된 이력서 버전 링크\n\n이력서 검토 및 개선 방법 피드백을 통한 개선과 지속적인 업데이트의 중요성 피드백 수렴 자신이 작성한 문서의 오류를 스스로 찾아내기란 쉽지 않습니다",
      "적인 내용의 정확성을 검증하고 , 프로젝트 경험이 명확하게 설명되었 는지 확인 멘토 및 선배 개발자 경력 기술 방식 ,  성과 부각 방법 등 전략적인 관점에서 조언 온라인 커뮤니티 Tech Interview Handbook  등 개발자 커뮤니티에서 이력서 리뷰를 서로 공 유 효과적인 피드백 요청 구체적인 조언을 구하는 것이 아니 라 ,  지원하는 직무와 회사 정보를 제 공 지속적인 업데이트 이력서는 한 번 만들고 끝나는 문서가 아니라 ,  자신의 성장을 담아내는 살아 있는 기록입니다",
      ",  실행 방법 ,  자신의 기여도 상세 히 설명 코드 품질 및 기여도 깔끔하고 주석이 잘 달린 코드 ,  오픈 소스에 기여하면 협업 능력 증명 LinkedIn  프로필 전문적인 네트워크를 구축하고 경력을 관리하는 필수 적 플랫폼 전문성 있는 프로필 이력서와 일관성 있는 경력 ,  학력 ,  기술 스택을 기재 네트워크 및 추천서 업계 전문가들과의 네트워크 ,  이전 동료나 상사의 추 천서 기술 및 보증",
      "스택은 별도 섹션으로 구성 경력은 가장 최근부터 역순으로 작성 프로젝트는 결과물을 확인할 수 있는 링크 포 함 간결하고 ,  명확하며 ,  직무와 관련성 높은 내용\n\n연락처 및 기술 스택 구성 전문적인 정보 표현으로 채용 담당자의 관심을 끄는 방법 연락처 정보 작성 이름 전체 이름을 명확하게 기재합니다",
      "블로그\n\n경력 및 프로젝트 작성법 구체적인 성과 중심으로 작성하는 방법과 수치화된 결과 제시 전략 경력 사항 작성법 구조와 포맷 회사명 ,  직책 ,  근무 기간 ,  위치 주요 성과",
      "스택 프로젝트 경력 교육 기술적 역량을 효과적으로 전달하는 이력서 작성법\n\n개발자 이력서 작성의 기본 이력서의 핵심 구성 요소와 효과적인 작성 방법 연락처 및 기본 정보 이름",
      "및 프로젝트 반영 새로운 프로그래밍 언어 ,  프레임워크를 학습하거나 의미 있는 프로젝트를 마쳤을 때 즉시 이력서에 추가 성과 기록 현재 진행 중인 업무에서 달성한 성과",
      "목록화하고 동료들로부터 보증 받으면 기 술적 신뢰성 강화 꾸준한 활동 기술 관련 아티클 공유하거나 토론에 참여하는 등 꾸 준한 활동 개인 블로그",
      "명시 프로젝트 경험 프로젝트명 및 기술 스택 프로젝트 목적 및 주요 기능 구체적인 역할과 기여 성과 및 결과",
      "은 사용한 경험이 있는 것부터 우선순위로 경력 사항 회사명 ,  직책 ,  근무 기간 ,  위치 주요 성과",
      "을 습득하거나 프로젝트를 완료할 때마다 이 력서를 꾸준히 업데이트하는 습관을 들이는 것이 중요합니다",
      "적 역량 ,  실무 경험 시니어 개발자 리더십 ,  멘토링 ,  프로젝트 관리 능력을 강조",
      ",  자격 요건을 파악 공고에 명시된 키워드를 자연스럽게 포함 약어와 전체 용어 병기",
      "블로그 등 자신의 코딩 실력과 프로젝트를 보여줄 수 있는 링크를 반드시 포함 합니다",
      "스택과 관련 수강 과목 채용 담당자가 확인하려는 것",
      "스택 요약 주요 프로젝트 고정",
      "적 깊이와 아키텍처 설계 능력",
      "스택과 문제 해결 능력 연결",
      "스택 구성 프로그래밍 언어",
      "스택 프로그래밍 언어",
      "스택 프로젝트 설명",
      "Kubernetes",
      "명시 예시 나쁜 예",
      "PostgreSQL",
      "적용 능력을 증명",
      "을 명시합니다",
      "을 나열합니다",
      "Node.js",
      "MongoDB",
      "Python",
      "데이터베이스",
      "Spring",
      "Docker",
      "Django",
      "DevOps",
      "React",
      "프론트엔드",
      "MySQL",
      "Java",
      "네트워크",
      "클라우드",
      "Git",
      "AWS",
      "마케팅",
      "C++",
      "Go"
    ],
    "addresses": [
      "닉네임이나 비전문적인 단어가 포함되지 않은 개인 이메일 주소를 사용 합니다",
      "전체 주소 대신 시와 구 단위까지만 기재하는 것이 일반적입니다",
      "서울특별시 강남구",
      "전화번호",
      "시"
    ]
  },
  "summary": "",
  "keywords": [],
  "created_at": "2025-08-13T17:26:44.024526"
}